pyrex/_pyrex.cpython-39-darwin.so
pyrex/__init__.py
pyrex/_pyrex.cpp
pyrex/.dylibs/libsnappy.1.2.2.dylib
pyrex/.dylibs/liblz4.1.10.0.dylib
pyrex/.dylibs/librocksdb.10.4.2.dylib
pyrex/.dylibs/libgflags.2.2.2.dylib
pyrex/.dylibs/libzstd.1.5.7.dylib
pyrex_rocksdb-0.1.4.dist-info/RECORD
pyrex_rocksdb-0.1.4.dist-info/WHEEL
pyrex_rocksdb-0.1.4.dist-info/top_level.txt
pyrex_rocksdb-0.1.4.dist-info/METADATA
pyrex_rocksdb-0.1.4.dist-info/licenses/LICENSE
