Metadata-Version: 2.4
Name: pyrex-rocksdb
Version: 0.1.4
Summary: A fast RocksDB wrapper for Python using pybind11.
Author-email: Charilaos Mylonas <mylonas.charilaos@gmail.com>
Project-URL: Homepage, https://github.com/mylonasc/pyrex
Project-URL: Repository, https://github.com/mylonasc/pyrex
Keywords: rocksdb,database,key-value,pybind11
Classifier: Programming Language :: Python :: 3
Classifier: Programming Language :: Python :: 3.8
Classifier: Programming Language :: Python :: 3.9
Classifier: Programming Language :: Python :: 3.10
Classifier: Programming Language :: Python :: 3.11
Classifier: Programming Language :: Python :: 3.12
Classifier: License :: OSI Approved :: Apache Software License
Classifier: Operating System :: POSIX :: Linux
Classifier: Operating System :: MacOS :: MacOS X
Classifier: Operating System :: Microsoft :: Windows
Classifier: Development Status :: 3 - Alpha
Classifier: Intended Audience :: Developers
Classifier: Topic :: Database
Requires-Python: >=3.8
License-File: LICENSE
Provides-Extra: dev
Requires-Dist: pytest; extra == "dev"
Requires-Dist: sphinx; extra == "dev"
Requires-Dist: sphinx-rtd-theme; extra == "dev"
Requires-Dist: cibuildwheel; extra == "dev"
Requires-Dist: pybind11-stubgen~=2.5.4; extra == "dev"
Requires-Dist: mypy~=1.10; extra == "dev"
Requires-Dist: twine; extra == "dev"
Dynamic: license-file
